rattingtax/__init__.py
rattingtax/admin.py
rattingtax/app_settings.py
rattingtax/apps.py
rattingtax/auth_hooks.py
rattingtax/esi.py
rattingtax/models.py
rattingtax/tasks.py
rattingtax/urls.py
rattingtax/views.py
rattingtax/locale/.gitkeep
rattingtax/migrations/0001_initial.py
rattingtax/migrations/0002_corpmonthstat_closed.py
rattingtax/migrations/0003_corpjournalentry.py
rattingtax/migrations/__init__.py
rattingtax/static/example/.gitkeep
rattingtax/templates/example/base.html
rattingtax/templates/example/index.html
rattingtax/templates/rattingtax/base.html
rattingtax/templates/rattingtax/dashboard.html
rattingtax/tests/__init__.py
rattingtax/tests/test_example.py
aa_rattingtax-1.0.6.dist-info/METADATA
aa_rattingtax-1.0.6.dist-info/WHEEL
aa_rattingtax-1.0.6.dist-info/licenses/LICENSE
aa_rattingtax-1.0.6.dist-info/RECORD
